librarium/__init__.py
librarium-0.0.1.dist-info/METADATA
librarium-0.0.1.dist-info/WHEEL
librarium-0.0.1.dist-info/RECORD
