Metadata-Version: 2.4
Name: librarium
Version: 0.0.1
Summary: library utilities
Author-email: Hans Gremmen <hans@leptonix.net>
License: MIT
Requires-Python: >=3.11
